directory_api_client/__init__.py
directory_api_client/base.py
directory_api_client/buyer.py
directory_api_client/client.py
directory_api_client/company.py
directory_api_client/dataservices.py
directory_api_client/enrolment.py
directory_api_client/exporting.py
directory_api_client/exportplan.py
directory_api_client/notifications.py
directory_api_client/personalisation.py
directory_api_client/supplier.py
directory_api_client/survey.py
directory_api_client/testapiclient.py
directory_api_client-26.15.1.dist-info/licenses/LICENSE
directory_api_client-26.15.1.dist-info/METADATA
directory_api_client-26.15.1.dist-info/WHEEL
directory_api_client-26.15.1.dist-info/top_level.txt
directory_api_client-26.15.1.dist-info/RECORD
