Metadata-Version: 2.4
Name: directory_api_client
Version: 26.15.1
Summary: Python client for Directory API.
Home-page: https://github.com/uktrade/directory-api-client
Author: Department for Business and Trade
License: MIT
Classifier: Development Status :: 5 - Production/Stable
Classifier: Environment :: Web Environment
Classifier: Framework :: Django
Classifier: Framework :: Django :: 4.2
Classifier: Intended Audience :: Developers
Classifier: License :: OSI Approved :: MIT License
Classifier: Natural Language :: English
Classifier: Operating System :: OS Independent
Classifier: Programming Language :: Python :: 3.9
Classifier: Programming Language :: Python :: 3.13
Classifier: Programming Language :: Python :: Implementation :: PyPy
Classifier: Topic :: Software Development :: Libraries :: Python Modules
License-File: LICENSE
Requires-Dist: django<5.0,>=4.2.10
Requires-Dist: requests<3.0.0,>=2.22.0
Requires-Dist: directory_client_core<8.0.0,>=7.2.12
Provides-Extra: test
Requires-Dist: pytest-cov; extra == "test"
Requires-Dist: pytest; extra == "test"
Requires-Dist: pytest-codecov; extra == "test"
Requires-Dist: GitPython; extra == "test"
Requires-Dist: requests_mock==1.7.0; extra == "test"
Requires-Dist: setuptools; extra == "test"
Requires-Dist: twine<4.0.0,>=3.1.1; extra == "test"
Requires-Dist: wheel<1.0.0,>=0.38.1; extra == "test"
Requires-Dist: black==22.10.0; extra == "test"
Requires-Dist: blacken-docs==1.6.0; extra == "test"
Requires-Dist: isort==5.6.4; extra == "test"
Requires-Dist: flake8==5.0.4; extra == "test"
Requires-Dist: pre-commit-hooks==3.3.0; extra == "test"
Dynamic: author
Dynamic: classifier
Dynamic: description
Dynamic: description-content-type
Dynamic: home-page
Dynamic: license
Dynamic: license-file
Dynamic: provides-extra
Dynamic: requires-dist
Dynamic: summary
